README.md
setup.cfg
setup.py
test/test_s3_backend.py
test/test_state_configurator.py
test/test_state_reader.py
tfoutputs/__init__.py
tfoutputs/backend.py
tfoutputs/state_reader.py
tfoutputs/stateconfigurator.py
tfoutputs.egg-info/PKG-INFO
tfoutputs.egg-info/SOURCES.txt
tfoutputs.egg-info/dependency_links.txt
tfoutputs.egg-info/requires.txt
tfoutputs.egg-info/top_level.txt