Metadata-Version: 1.1
Name: tfoutputs
Version: 0.0.3
Summary: A library to get your terraform outputs in your python code
Home-page: https://github.com/jae2/python-tfoutputs
Author: James Edwards
Author-email: admin@jaetech.org
License: MIT
Platform: UNKNOWN
Classifier: Development Status :: 3 - Alpha
Classifier: Intended Audience :: Developers
Classifier: Intended Audience :: Information Technology
Classifier: Intended Audience :: System Administrators
Classifier: License :: OSI Approved :: MIT License
Classifier: Programming Language :: Python :: 3.3
Classifier: Programming Language :: Python :: 3.4
Classifier: Programming Language :: Python :: 3.5
Classifier: Programming Language :: Python :: 3.6
